daves_utilities/__init__.py
daves_utilities/credentials.py
daves_utilities/david_secrets.py
daves_utilities/db.py
daves_utilities/kubernetes.py
daves_utilities-0.1.16.dist-info/LICENSE
daves_utilities-0.1.16.dist-info/METADATA
daves_utilities-0.1.16.dist-info/WHEEL
daves_utilities-0.1.16.dist-info/RECORD
