Metadata-Version: 2.1
Name: daves-utilities
Version: 0.1.16
Summary: some useful function for myself
Home-page: https://github.com/kuchedav/daves_utilities
License: MIT
Keywords: packaging,poetry
Author: David Kuchelmeister
Requires-Python: >=3.11,<4.0
Classifier: License :: OSI Approved :: MIT License
Classifier: Programming Language :: Python :: 3
Classifier: Programming Language :: Python :: 3.11
Requires-Dist: build (>=0.10.0,<0.11.0)
Requires-Dist: bumpversion (>=0.6.0,<0.7.0)
Requires-Dist: cryptography (>=41.0.2,<42.0.0)
Requires-Dist: detect-secrets (>=1.4.0,<2.0.0)
Requires-Dist: flake8 (>=6.0.0,<7.0.0)
Requires-Dist: mypy (>=1.4.1,<2.0.0)
Requires-Dist: pre-commit (>=3.3.3,<4.0.0)
Requires-Dist: pre-commit-hooks (>=4.4.0,<5.0.0)
Requires-Dist: pytest (>=8.1.1,<9.0.0)
Requires-Dist: pyupgrade (>=3.9.0,<4.0.0)
Requires-Dist: reorder-python-imports (>=3.10.0,<4.0.0)
Requires-Dist: ruff (>=0.0.278,<0.0.279)
Requires-Dist: setuptools-scm (>=7.1.0,<8.0.0)
Requires-Dist: tox (>=4.6.4,<5.0.0)
Requires-Dist: twine (>=4.0.2,<5.0.0)
Requires-Dist: typeguard (>=4.2.1,<5.0.0)
Requires-Dist: wheel (>=0.40.0,<0.41.0)
Project-URL: Repository, https://github.com/kuchedav/daves_utilities
